grimsel/__init__.py
grimsel/grimsel_config.py
grimsel/auxiliary/__init__.py
grimsel/auxiliary/aux_general.py
grimsel/auxiliary/aux_m_func.py
grimsel/auxiliary/build_utils.py
grimsel/auxiliary/maps.py
grimsel/auxiliary/multiproc.py
grimsel/auxiliary/timemap.py
grimsel/auxiliary/sqlutils/__init__.py
grimsel/auxiliary/sqlutils/aux_sql_func.py
grimsel/core/__init__.py
grimsel/core/autocomplete.py
grimsel/core/constraints.py
grimsel/core/io.py
grimsel/core/model_base.py
grimsel/core/model_loop.py
grimsel/core/model_loop_modifier.py
grimsel/core/parameters.py
grimsel/core/sets.py
grimsel/core/table_struct.py
grimsel/core/variables.py
Grimsel-0.9.0.dist-info/AUTHORS.rst
Grimsel-0.9.0.dist-info/LICENSE
Grimsel-0.9.0.dist-info/METADATA
Grimsel-0.9.0.dist-info/WHEEL
Grimsel-0.9.0.dist-info/top_level.txt
Grimsel-0.9.0.dist-info/RECORD
