Metadata-Version: 2.1
Name: Grimsel
Version: 0.9.0
Summary: GeneRal Integrated Modeling environment for the Supply of Electricity and Low-temperature heat
Home-page: https://github.com/mcsoini/grimsel
Author: Grimsel contributors listed in AUTHORS
Author-email: mcsoini_dev@posteo.org
License: UNKNOWN
Platform: UNKNOWN
Classifier: Programming Language :: Python :: 3.8
Classifier: Operating System :: OS Independent
Requires-Dist: pyutilib (>=5.8.0)
Requires-Dist: pandas (>=1.0.0)
Requires-Dist: pyomo (==5.6.9)
Requires-Dist: wrapt (>=1.12.1)
Requires-Dist: psycopg2 (>=2.8.5)
Requires-Dist: numpy (>=1.18.2)
Requires-Dist: sqlalchemy (>=1.3.16)
Requires-Dist: statsmodels (>=0.11.1)
Requires-Dist: tables (>=3.6.1)
Requires-Dist: fastparquet (>=0.3.3)
Requires-Dist: matplotlib (>=3.2.1)
Requires-Dist: tabulate (>=0.8.7)
